osgb/__init__.py
osgb/convert.py
osgb/gb_coastline.shapes
osgb/gridder.py
osgb/legacy_interface.py
osgb/mapping.data
osgb/mapping.py
osgb/ostn02.data
osgb/ostn_east_shift_82140
osgb/ostn_north_shift_-84180
osgb-1.0.0.data/scripts/bngl
osgb-1.0.0.data/scripts/plot_maps.py
osgb-1.0.0.data/scripts/whatmaps.py
osgb-1.0.0.dist-info/METADATA
osgb-1.0.0.dist-info/RECORD
osgb-1.0.0.dist-info/WHEEL
osgb-1.0.0.dist-info/top_level.txt
